[
  {
    "type": "constructor",
    "inputs": [
      {
        "name": "_platformFeeBps",
        "type": "uint16",
        "internalType": "uint16"
      }
    ],
    "stateMutability": "nonpayable"
  },
  {
    "type": "function",
    "name": "BPS_TOTAL",
    "inputs": [],
    "outputs": [
      {
        "name": "",
        "type": "uint256",
        "internalType": "uint256"
      }
    ],
    "stateMutability": "view"
  },
  {
    "type": "function",
    "name": "MAX_PLATFORM_FEE_BPS",
    "inputs": [],
    "outputs": [
      {
        "name": "",
        "type": "uint16",
        "internalType": "uint16"
      }
    ],
    "stateMutability": "view"
  },
  {
    "type": "function",
    "name": "MAX_PLAYERS",
    "inputs": [],
    "outputs": [
      {
        "name": "",
        "type": "uint16",
        "internalType": "uint16"
      }
    ],
    "stateMutability": "view"
  },
  {
    "type": "function",
    "name": "MAX_TITLE_LENGTH",
    "inputs": [],
    "outputs": [
      {
        "name": "",
        "type": "uint256",
        "internalType": "uint256"
      }
    ],
    "stateMutability": "view"
  },
  {
    "type": "function",
    "name": "addOperator",
    "inputs": [
      {
        "name": "op",
        "type": "address",
        "internalType": "address"
      }
    ],
    "outputs": [],
    "stateMutability": "nonpayable"
  },
  {
    "type": "function",
    "name": "claimPrize",
    "inputs": [
      {
        "name": "gameId",
        "type": "uint256",
        "internalType": "uint256"
      }
    ],
    "outputs": [],
    "stateMutability": "nonpayable"
  },
  {
    "type": "function",
    "name": "claimRefund",
    "inputs": [
      {
        "name": "gameId",
        "type": "uint256",
        "internalType": "uint256"
      }
    ],
    "outputs": [],
    "stateMutability": "nonpayable"
  },
  {
    "type": "function",
    "name": "createGame",
    "inputs": [
      {
        "name": "params",
        "type": "tuple",
        "internalType": "struct IChainAssassin.CreateGameParams",
        "components": [
          {
            "name": "title",
            "type": "string",
            "internalType": "string"
          },
          {
            "name": "entryFee",
            "type": "uint128",
            "internalType": "uint128"
          },
          {
            "name": "minPlayers",
            "type": "uint16",
            "internalType": "uint16"
          },
          {
            "name": "maxPlayers",
            "type": "uint16",
            "internalType": "uint16"
          },
          {
            "name": "registrationDeadline",
            "type": "uint40",
            "internalType": "uint40"
          },
          {
            "name": "gameDate",
            "type": "uint40",
            "internalType": "uint40"
          },
          {
            "name": "maxDuration",
            "type": "uint32",
            "internalType": "uint32"
          },
          {
            "name": "centerLat",
            "type": "int32",
            "internalType": "int32"
          },
          {
            "name": "centerLng",
            "type": "int32",
            "internalType": "int32"
          },
          {
            "name": "bps1st",
            "type": "uint16",
            "internalType": "uint16"
          },
          {
            "name": "bps2nd",
            "type": "uint16",
            "internalType": "uint16"
          },
          {
            "name": "bps3rd",
            "type": "uint16",
            "internalType": "uint16"
          },
          {
            "name": "bpsKills",
            "type": "uint16",
            "internalType": "uint16"
          },
          {
            "name": "bpsCreator",
            "type": "uint16",
            "internalType": "uint16"
          }
        ]
      },
      {
        "name": "shrinks",
        "type": "tuple[]",
        "internalType": "struct IChainAssassin.ZoneShrink[]",
        "components": [
          {
            "name": "atSecond",
            "type": "uint32",
            "internalType": "uint32"
          },
          {
            "name": "radiusMeters",
            "type": "uint32",
            "internalType": "uint32"
          }
        ]
      }
    ],
    "outputs": [
      {
        "name": "gameId",
        "type": "uint256",
        "internalType": "uint256"
      }
    ],
    "stateMutability": "nonpayable"
  },
  {
    "type": "function",
    "name": "creatorFeesAccrued",
    "inputs": [
      {
        "name": "",
        "type": "address",
        "internalType": "address"
      }
    ],
    "outputs": [
      {
        "name": "",
        "type": "uint256",
        "internalType": "uint256"
      }
    ],
    "stateMutability": "view"
  },
  {
    "type": "function",
    "name": "eliminatePlayer",
    "inputs": [
      {
        "name": "gameId",
        "type": "uint256",
        "internalType": "uint256"
      },
      {
        "name": "player",
        "type": "address",
        "internalType": "address"
      }
    ],
    "outputs": [],
    "stateMutability": "nonpayable"
  },
  {
    "type": "function",
    "name": "endGame",
    "inputs": [
      {
        "name": "gameId",
        "type": "uint256",
        "internalType": "uint256"
      },
      {
        "name": "winner1",
        "type": "address",
        "internalType": "address"
      },
      {
        "name": "winner2",
        "type": "address",
        "internalType": "address"
      },
      {
        "name": "winner3",
        "type": "address",
        "internalType": "address"
      },
      {
        "name": "topKiller",
        "type": "address",
        "internalType": "address"
      }
    ],
    "outputs": [],
    "stateMutability": "nonpayable"
  },
  {
    "type": "function",
    "name": "getClaimableAmount",
    "inputs": [
      {
        "name": "gameId",
        "type": "uint256",
        "internalType": "uint256"
      },
      {
        "name": "player",
        "type": "address",
        "internalType": "address"
      }
    ],
    "outputs": [
      {
        "name": "",
        "type": "uint256",
        "internalType": "uint256"
      }
    ],
    "stateMutability": "view"
  },
  {
    "type": "function",
    "name": "getGameConfig",
    "inputs": [
      {
        "name": "gameId",
        "type": "uint256",
        "internalType": "uint256"
      }
    ],
    "outputs": [
      {
        "name": "",
        "type": "tuple",
        "internalType": "struct IChainAssassin.GameConfig",
        "components": [
          {
            "name": "title",
            "type": "string",
            "internalType": "string"
          },
          {
            "name": "entryFee",
            "type": "uint128",
            "internalType": "uint128"
          },
          {
            "name": "minPlayers",
            "type": "uint16",
            "internalType": "uint16"
          },
          {
            "name": "maxPlayers",
            "type": "uint16",
            "internalType": "uint16"
          },
          {
            "name": "registrationDeadline",
            "type": "uint40",
            "internalType": "uint40"
          },
          {
            "name": "gameDate",
            "type": "uint40",
            "internalType": "uint40"
          },
          {
            "name": "maxDuration",
            "type": "uint32",
            "internalType": "uint32"
          },
          {
            "name": "createdAt",
            "type": "uint40",
            "internalType": "uint40"
          },
          {
            "name": "creator",
            "type": "address",
            "internalType": "address"
          },
          {
            "name": "centerLat",
            "type": "int32",
            "internalType": "int32"
          },
          {
            "name": "centerLng",
            "type": "int32",
            "internalType": "int32"
          },
          {
            "name": "bps1st",
            "type": "uint16",
            "internalType": "uint16"
          },
          {
            "name": "bps2nd",
            "type": "uint16",
            "internalType": "uint16"
          },
          {
            "name": "bps3rd",
            "type": "uint16",
            "internalType": "uint16"
          },
          {
            "name": "bpsKills",
            "type": "uint16",
            "internalType": "uint16"
          },
          {
            "name": "bpsCreator",
            "type": "uint16",
            "internalType": "uint16"
          }
        ]
      }
    ],
    "stateMutability": "view"
  },
  {
    "type": "function",
    "name": "getGameState",
    "inputs": [
      {
        "name": "gameId",
        "type": "uint256",
        "internalType": "uint256"
      }
    ],
    "outputs": [
      {
        "name": "",
        "type": "tuple",
        "internalType": "struct IChainAssassin.GameState",
        "components": [
          {
            "name": "phase",
            "type": "uint8",
            "internalType": "enum IChainAssassin.GamePhase"
          },
          {
            "name": "playerCount",
            "type": "uint16",
            "internalType": "uint16"
          },
          {
            "name": "totalCollected",
            "type": "uint128",
            "internalType": "uint128"
          },
          {
            "name": "winner1",
            "type": "address",
            "internalType": "address"
          },
          {
            "name": "winner2",
            "type": "address",
            "internalType": "address"
          },
          {
            "name": "winner3",
            "type": "address",
            "internalType": "address"
          },
          {
            "name": "topKiller",
            "type": "address",
            "internalType": "address"
          }
        ]
      }
    ],
    "stateMutability": "view"
  },
  {
    "type": "function",
    "name": "getPlayerInfo",
    "inputs": [
      {
        "name": "gameId",
        "type": "uint256",
        "internalType": "uint256"
      },
      {
        "name": "player",
        "type": "address",
        "internalType": "address"
      }
    ],
    "outputs": [
      {
        "name": "registered",
        "type": "bool",
        "internalType": "bool"
      },
      {
        "name": "alive",
        "type": "bool",
        "internalType": "bool"
      },
      {
        "name": "kills",
        "type": "uint16",
        "internalType": "uint16"
      },
      {
        "name": "claimed",
        "type": "bool",
        "internalType": "bool"
      },
      {
        "name": "number",
        "type": "uint16",
        "internalType": "uint16"
      }
    ],
    "stateMutability": "view"
  },
  {
    "type": "function",
    "name": "getZoneShrinks",
    "inputs": [
      {
        "name": "gameId",
        "type": "uint256",
        "internalType": "uint256"
      }
    ],
    "outputs": [
      {
        "name": "",
        "type": "tuple[]",
        "internalType": "struct IChainAssassin.ZoneShrink[]",
        "components": [
          {
            "name": "atSecond",
            "type": "uint32",
            "internalType": "uint32"
          },
          {
            "name": "radiusMeters",
            "type": "uint32",
            "internalType": "uint32"
          }
        ]
      }
    ],
    "stateMutability": "view"
  },
  {
    "type": "function",
    "name": "hasClaimed",
    "inputs": [
      {
        "name": "",
        "type": "uint256",
        "internalType": "uint256"
      },
      {
        "name": "",
        "type": "address",
        "internalType": "address"
      }
    ],
    "outputs": [
      {
        "name": "",
        "type": "bool",
        "internalType": "bool"
      }
    ],
    "stateMutability": "view"
  },
  {
    "type": "function",
    "name": "isAlive",
    "inputs": [
      {
        "name": "",
        "type": "uint256",
        "internalType": "uint256"
      },
      {
        "name": "",
        "type": "address",
        "internalType": "address"
      }
    ],
    "outputs": [
      {
        "name": "",
        "type": "bool",
        "internalType": "bool"
      }
    ],
    "stateMutability": "view"
  },
  {
    "type": "function",
    "name": "isOperator",
    "inputs": [
      {
        "name": "",
        "type": "address",
        "internalType": "address"
      }
    ],
    "outputs": [
      {
        "name": "",
        "type": "bool",
        "internalType": "bool"
      }
    ],
    "stateMutability": "view"
  },
  {
    "type": "function",
    "name": "isRegistered",
    "inputs": [
      {
        "name": "",
        "type": "uint256",
        "internalType": "uint256"
      },
      {
        "name": "",
        "type": "address",
        "internalType": "address"
      }
    ],
    "outputs": [
      {
        "name": "",
        "type": "bool",
        "internalType": "bool"
      }
    ],
    "stateMutability": "view"
  },
  {
    "type": "function",
    "name": "killCount",
    "inputs": [
      {
        "name": "",
        "type": "uint256",
        "internalType": "uint256"
      },
      {
        "name": "",
        "type": "address",
        "internalType": "address"
      }
    ],
    "outputs": [
      {
        "name": "",
        "type": "uint16",
        "internalType": "uint16"
      }
    ],
    "stateMutability": "view"
  },
  {
    "type": "function",
    "name": "nextGameId",
    "inputs": [],
    "outputs": [
      {
        "name": "",
        "type": "uint256",
        "internalType": "uint256"
      }
    ],
    "stateMutability": "view"
  },
  {
    "type": "function",
    "name": "owner",
    "inputs": [],
    "outputs": [
      {
        "name": "",
        "type": "address",
        "internalType": "address"
      }
    ],
    "stateMutability": "view"
  },
  {
    "type": "function",
    "name": "platformFeeBps",
    "inputs": [],
    "outputs": [
      {
        "name": "",
        "type": "uint16",
        "internalType": "uint16"
      }
    ],
    "stateMutability": "view"
  },
  {
    "type": "function",
    "name": "platformFeesAccrued",
    "inputs": [],
    "outputs": [
      {
        "name": "",
        "type": "uint256",
        "internalType": "uint256"
      }
    ],
    "stateMutability": "view"
  },
  {
    "type": "function",
    "name": "playerNumber",
    "inputs": [
      {
        "name": "",
        "type": "uint256",
        "internalType": "uint256"
      },
      {
        "name": "",
        "type": "address",
        "internalType": "address"
      }
    ],
    "outputs": [
      {
        "name": "",
        "type": "uint16",
        "internalType": "uint16"
      }
    ],
    "stateMutability": "view"
  },
  {
    "type": "function",
    "name": "recordKill",
    "inputs": [
      {
        "name": "gameId",
        "type": "uint256",
        "internalType": "uint256"
      },
      {
        "name": "hunter",
        "type": "address",
        "internalType": "address"
      },
      {
        "name": "target",
        "type": "address",
        "internalType": "address"
      }
    ],
    "outputs": [],
    "stateMutability": "nonpayable"
  },
  {
    "type": "function",
    "name": "register",
    "inputs": [
      {
        "name": "gameId",
        "type": "uint256",
        "internalType": "uint256"
      }
    ],
    "outputs": [],
    "stateMutability": "payable"
  },
  {
    "type": "function",
    "name": "removeOperator",
    "inputs": [
      {
        "name": "op",
        "type": "address",
        "internalType": "address"
      }
    ],
    "outputs": [],
    "stateMutability": "nonpayable"
  },
  {
    "type": "function",
    "name": "renounceOwnership",
    "inputs": [],
    "outputs": [],
    "stateMutability": "nonpayable"
  },
  {
    "type": "function",
    "name": "setPlatformFeeBps",
    "inputs": [
      {
        "name": "newBps",
        "type": "uint16",
        "internalType": "uint16"
      }
    ],
    "outputs": [],
    "stateMutability": "nonpayable"
  },
  {
    "type": "function",
    "name": "startGame",
    "inputs": [
      {
        "name": "gameId",
        "type": "uint256",
        "internalType": "uint256"
      }
    ],
    "outputs": [],
    "stateMutability": "nonpayable"
  },
  {
    "type": "function",
    "name": "transferOwnership",
    "inputs": [
      {
        "name": "newOwner",
        "type": "address",
        "internalType": "address"
      }
    ],
    "outputs": [],
    "stateMutability": "nonpayable"
  },
  {
    "type": "function",
    "name": "triggerCancellation",
    "inputs": [
      {
        "name": "gameId",
        "type": "uint256",
        "internalType": "uint256"
      }
    ],
    "outputs": [],
    "stateMutability": "nonpayable"
  },
  {
    "type": "function",
    "name": "triggerExpiry",
    "inputs": [
      {
        "name": "gameId",
        "type": "uint256",
        "internalType": "uint256"
      }
    ],
    "outputs": [],
    "stateMutability": "nonpayable"
  },
  {
    "type": "function",
    "name": "withdrawCreatorFees",
    "inputs": [
      {
        "name": "to",
        "type": "address",
        "internalType": "address"
      }
    ],
    "outputs": [],
    "stateMutability": "nonpayable"
  },
  {
    "type": "function",
    "name": "withdrawPlatformFees",
    "inputs": [
      {
        "name": "to",
        "type": "address",
        "internalType": "address"
      }
    ],
    "outputs": [],
    "stateMutability": "nonpayable"
  },
  {
    "type": "event",
    "name": "CreatorFeesWithdrawn",
    "inputs": [
      {
        "name": "creator",
        "type": "address",
        "indexed": true,
        "internalType": "address"
      },
      {
        "name": "to",
        "type": "address",
        "indexed": true,
        "internalType": "address"
      },
      {
        "name": "amount",
        "type": "uint256",
        "indexed": false,
        "internalType": "uint256"
      }
    ],
    "anonymous": false
  },
  {
    "type": "event",
    "name": "GameCancelled",
    "inputs": [
      {
        "name": "gameId",
        "type": "uint256",
        "indexed": true,
        "internalType": "uint256"
      }
    ],
    "anonymous": false
  },
  {
    "type": "event",
    "name": "GameCreated",
    "inputs": [
      {
        "name": "gameId",
        "type": "uint256",
        "indexed": true,
        "internalType": "uint256"
      },
      {
        "name": "title",
        "type": "string",
        "indexed": false,
        "internalType": "string"
      },
      {
        "name": "entryFee",
        "type": "uint128",
        "indexed": false,
        "internalType": "uint128"
      },
      {
        "name": "minPlayers",
        "type": "uint16",
        "indexed": false,
        "internalType": "uint16"
      },
      {
        "name": "maxPlayers",
        "type": "uint16",
        "indexed": false,
        "internalType": "uint16"
      },
      {
        "name": "centerLat",
        "type": "int32",
        "indexed": false,
        "internalType": "int32"
      },
      {
        "name": "centerLng",
        "type": "int32",
        "indexed": false,
        "internalType": "int32"
      }
    ],
    "anonymous": false
  },
  {
    "type": "event",
    "name": "GameEnded",
    "inputs": [
      {
        "name": "gameId",
        "type": "uint256",
        "indexed": true,
        "internalType": "uint256"
      },
      {
        "name": "winner1",
        "type": "address",
        "indexed": false,
        "internalType": "address"
      },
      {
        "name": "winner2",
        "type": "address",
        "indexed": false,
        "internalType": "address"
      },
      {
        "name": "winner3",
        "type": "address",
        "indexed": false,
        "internalType": "address"
      },
      {
        "name": "topKiller",
        "type": "address",
        "indexed": false,
        "internalType": "address"
      }
    ],
    "anonymous": false
  },
  {
    "type": "event",
    "name": "GameStarted",
    "inputs": [
      {
        "name": "gameId",
        "type": "uint256",
        "indexed": true,
        "internalType": "uint256"
      },
      {
        "name": "playerCount",
        "type": "uint16",
        "indexed": false,
        "internalType": "uint16"
      }
    ],
    "anonymous": false
  },
  {
    "type": "event",
    "name": "KillRecorded",
    "inputs": [
      {
        "name": "gameId",
        "type": "uint256",
        "indexed": true,
        "internalType": "uint256"
      },
      {
        "name": "hunter",
        "type": "address",
        "indexed": true,
        "internalType": "address"
      },
      {
        "name": "target",
        "type": "address",
        "indexed": true,
        "internalType": "address"
      }
    ],
    "anonymous": false
  },
  {
    "type": "event",
    "name": "OperatorAdded",
    "inputs": [
      {
        "name": "operator",
        "type": "address",
        "indexed": true,
        "internalType": "address"
      }
    ],
    "anonymous": false
  },
  {
    "type": "event",
    "name": "OperatorRemoved",
    "inputs": [
      {
        "name": "operator",
        "type": "address",
        "indexed": true,
        "internalType": "address"
      }
    ],
    "anonymous": false
  },
  {
    "type": "event",
    "name": "OwnershipTransferred",
    "inputs": [
      {
        "name": "previousOwner",
        "type": "address",
        "indexed": true,
        "internalType": "address"
      },
      {
        "name": "newOwner",
        "type": "address",
        "indexed": true,
        "internalType": "address"
      }
    ],
    "anonymous": false
  },
  {
    "type": "event",
    "name": "PlatformFeeBpsUpdated",
    "inputs": [
      {
        "name": "oldBps",
        "type": "uint16",
        "indexed": false,
        "internalType": "uint16"
      },
      {
        "name": "newBps",
        "type": "uint16",
        "indexed": false,
        "internalType": "uint16"
      }
    ],
    "anonymous": false
  },
  {
    "type": "event",
    "name": "PlatformFeesWithdrawn",
    "inputs": [
      {
        "name": "to",
        "type": "address",
        "indexed": true,
        "internalType": "address"
      },
      {
        "name": "amount",
        "type": "uint256",
        "indexed": false,
        "internalType": "uint256"
      }
    ],
    "anonymous": false
  },
  {
    "type": "event",
    "name": "PlayerEliminated",
    "inputs": [
      {
        "name": "gameId",
        "type": "uint256",
        "indexed": true,
        "internalType": "uint256"
      },
      {
        "name": "player",
        "type": "address",
        "indexed": true,
        "internalType": "address"
      },
      {
        "name": "eliminator",
        "type": "address",
        "indexed": true,
        "internalType": "address"
      }
    ],
    "anonymous": false
  },
  {
    "type": "event",
    "name": "PlayerRegistered",
    "inputs": [
      {
        "name": "gameId",
        "type": "uint256",
        "indexed": true,
        "internalType": "uint256"
      },
      {
        "name": "player",
        "type": "address",
        "indexed": true,
        "internalType": "address"
      },
      {
        "name": "playerCount",
        "type": "uint16",
        "indexed": false,
        "internalType": "uint16"
      }
    ],
    "anonymous": false
  },
  {
    "type": "event",
    "name": "PrizeClaimed",
    "inputs": [
      {
        "name": "gameId",
        "type": "uint256",
        "indexed": true,
        "internalType": "uint256"
      },
      {
        "name": "player",
        "type": "address",
        "indexed": true,
        "internalType": "address"
      },
      {
        "name": "amount",
        "type": "uint256",
        "indexed": false,
        "internalType": "uint256"
      }
    ],
    "anonymous": false
  },
  {
    "type": "event",
    "name": "RefundClaimed",
    "inputs": [
      {
        "name": "gameId",
        "type": "uint256",
        "indexed": true,
        "internalType": "uint256"
      },
      {
        "name": "player",
        "type": "address",
        "indexed": true,
        "internalType": "address"
      },
      {
        "name": "amount",
        "type": "uint256",
        "indexed": false,
        "internalType": "uint256"
      }
    ],
    "anonymous": false
  },
  {
    "type": "error",
    "name": "AlreadyClaimed",
    "inputs": []
  },
  {
    "type": "error",
    "name": "AlreadyRegistered",
    "inputs": []
  },
  {
    "type": "error",
    "name": "BpsSumNot10000",
    "inputs": []
  },
  {
    "type": "error",
    "name": "CannotSelfKill",
    "inputs": []
  },
  {
    "type": "error",
    "name": "DeadlineInPast",
    "inputs": []
  },
  {
    "type": "error",
    "name": "DeadlineNotPassed",
    "inputs": []
  },
  {
    "type": "error",
    "name": "EnoughPlayers",
    "inputs": []
  },
  {
    "type": "error",
    "name": "FirstShrinkMustBeZero",
    "inputs": []
  },
  {
    "type": "error",
    "name": "GameDateNotAfterDeadline",
    "inputs": []
  },
  {
    "type": "error",
    "name": "GameDateNotReached",
    "inputs": []
  },
  {
    "type": "error",
    "name": "GameFull",
    "inputs": []
  },
  {
    "type": "error",
    "name": "HunterNotAlive",
    "inputs": []
  },
  {
    "type": "error",
    "name": "HunterNotRegistered",
    "inputs": []
  },
  {
    "type": "error",
    "name": "MaxDurationZero",
    "inputs": []
  },
  {
    "type": "error",
    "name": "MaxLessThanMin",
    "inputs": []
  },
  {
    "type": "error",
    "name": "MaxPlayersTooHigh",
    "inputs": []
  },
  {
    "type": "error",
    "name": "MaxPlayersTooLow",
    "inputs": []
  },
  {
    "type": "error",
    "name": "MinPlayersLessThanPrizeSlots",
    "inputs": []
  },
  {
    "type": "error",
    "name": "MinPlayersTooLow",
    "inputs": []
  },
  {
    "type": "error",
    "name": "Need2ndIf3rdSet",
    "inputs": []
  },
  {
    "type": "error",
    "name": "NeedFirstPrize",
    "inputs": []
  },
  {
    "type": "error",
    "name": "NoFees",
    "inputs": []
  },
  {
    "type": "error",
    "name": "NoPrize",
    "inputs": []
  },
  {
    "type": "error",
    "name": "NoShrinkSchedule",
    "inputs": []
  },
  {
    "type": "error",
    "name": "NotEnoughPlayers",
    "inputs": []
  },
  {
    "type": "error",
    "name": "NotExpiredYet",
    "inputs": []
  },
  {
    "type": "error",
    "name": "NotOperator",
    "inputs": []
  },
  {
    "type": "error",
    "name": "OwnableInvalidOwner",
    "inputs": [
      {
        "name": "owner",
        "type": "address",
        "internalType": "address"
      }
    ]
  },
  {
    "type": "error",
    "name": "OwnableUnauthorizedAccount",
    "inputs": [
      {
        "name": "account",
        "type": "address",
        "internalType": "address"
      }
    ]
  },
  {
    "type": "error",
    "name": "PlatformFeeTooHigh",
    "inputs": []
  },
  {
    "type": "error",
    "name": "PlayerNotAlive",
    "inputs": []
  },
  {
    "type": "error",
    "name": "PlayerNotRegistered",
    "inputs": []
  },
  {
    "type": "error",
    "name": "RadiiNotDecreasing",
    "inputs": []
  },
  {
    "type": "error",
    "name": "ReentrancyGuardReentrantCall",
    "inputs": []
  },
  {
    "type": "error",
    "name": "RegistrationClosed",
    "inputs": []
  },
  {
    "type": "error",
    "name": "ShrinksNotOrdered",
    "inputs": []
  },
  {
    "type": "error",
    "name": "TargetNotAlive",
    "inputs": []
  },
  {
    "type": "error",
    "name": "TargetNotRegistered",
    "inputs": []
  },
  {
    "type": "error",
    "name": "TitleTooLong",
    "inputs": []
  },
  {
    "type": "error",
    "name": "TopKillerNotRegistered",
    "inputs": []
  },
  {
    "type": "error",
    "name": "TopKillerZeroAddress",
    "inputs": []
  },
  {
    "type": "error",
    "name": "TransferFailed",
    "inputs": []
  },
  {
    "type": "error",
    "name": "UnusedTopKillerNotZero",
    "inputs": []
  },
  {
    "type": "error",
    "name": "UnusedWinnerNotZero",
    "inputs": []
  },
  {
    "type": "error",
    "name": "WinnerNotRegistered",
    "inputs": []
  },
  {
    "type": "error",
    "name": "WinnerZeroAddress",
    "inputs": []
  },
  {
    "type": "error",
    "name": "WinnersNotUnique",
    "inputs": []
  },
  {
    "type": "error",
    "name": "WrongEntryFee",
    "inputs": []
  },
  {
    "type": "error",
    "name": "WrongPhase",
    "inputs": []
  },
  {
    "type": "error",
    "name": "ZeroAddress",
    "inputs": []
  }
]